similarweb_rest_api/__init__.py
similarweb_rest_api/similarweb_endpoints.json
similarweb_rest_api/similarweb_rest_api.py
similarweb_rest_api-0.1.1.dist-info/LICENSE
similarweb_rest_api-0.1.1.dist-info/METADATA
similarweb_rest_api-0.1.1.dist-info/WHEEL
similarweb_rest_api-0.1.1.dist-info/top_level.txt
similarweb_rest_api-0.1.1.dist-info/RECORD
