Metadata-Version: 2.1
Name: similarweb-rest-api
Version: 0.1.1
Summary: A library to simplify the access to the REST API of similarweb.
Home-page: https://github.com/DamienDrash/similarweb_rest_api
Author: Damien Frigewski
Author-email: Damien Frigewski <dfrigewski@gmail.com>
License: MIT
Project-URL: Homepage, https://github.com/DamienDrash/similarweb_rest_api
Project-URL: Bug Tracker, https://github.com/DamienDrash/similarweb_rest_api/issues
Classifier: Programming Language :: Python :: 3
Classifier: License :: OSI Approved :: MIT License
Classifier: Operating System :: OS Independent
Requires-Python: >=3.6
License-File: LICENSE
Requires-Dist: pandas
Requires-Dist: requests
Requires-Dist: lxml
Requires-Dist: pyyaml
